lrt_wallbox/__init__.py
lrt_wallbox/exceptions.py
lrt_wallbox/wallbox.py
lrt_wallbox/msg_types/__init__.py
lrt_wallbox/msg_types/atmel.py
lrt_wallbox/msg_types/auth_key.py
lrt_wallbox/msg_types/auth_password.py
lrt_wallbox/msg_types/config_load.py
lrt_wallbox/msg_types/config_network.py
lrt_wallbox/msg_types/config_ocpp.py
lrt_wallbox/msg_types/helpers.py
lrt_wallbox/msg_types/info.py
lrt_wallbox/msg_types/message.py
lrt_wallbox/msg_types/rfid.py
lrt_wallbox/msg_types/setup.py
lrt_wallbox/msg_types/transaction.py
lrt_wallbox/msg_types/user.py
lrt_wallbox/msg_types/util.py
lrt_wallbox-0.1.7.dist-info/licenses/LICENSE
lrt_wallbox-0.1.7.dist-info/METADATA
lrt_wallbox-0.1.7.dist-info/WHEEL
lrt_wallbox-0.1.7.dist-info/top_level.txt
lrt_wallbox-0.1.7.dist-info/RECORD
