Metadata-Version: 2.4
Name: lrt_wallbox
Version: 0.1.7
Summary: A Python client for interacting with LRT Wallbox devices via HTTP API.
Author-email: Kacper <8o9tddfam@mozmail.com>
License:                     GNU GENERAL PUBLIC LICENSE
Project-URL: Homepage, https://github.com/Upgreydd/lrt_wallbox
Project-URL: Repository, https://github.com/Upgreydd/lrt_wallbox
Keywords: wallbox,ev,ocpp,api,lrt,aeg
Classifier: Programming Language :: Python :: 3
Classifier: License :: OSI Approved :: MIT License
Classifier: Operating System :: OS Independent
Requires-Python: >=3.8
License-File: LICENSE
Requires-Dist: cbor2==5.6.5
Requires-Dist: requests==2.32.4
Requires-Dist: cryptography==45.0.3
Dynamic: license-file
